Workbook

Sheet Exports_Summary
A1: Ethiopian Coffee Exporters' Association
A2: Monthly Exported Volume and Value of Coffee
A3: Volumes in TONS green
A4: Values in USD (thousands)
G6: First year of ECX trading
A7: No. | B7: Month | C7: 2010/11 | E7: 2009/10 | G7: 2008/09 | I7: 2007/08 | K7: 2006/07 | M7: 2005/06 | O7: 2004/05 | Q7: 2003/04
C8: Volume | D8: Value | E8: Volume | F8: Value | G8: Volume | H8: Value | I8: Volume | J8: Value | K8: Volume | L8: Value | M8: Volume | N8: Value | O8: Volume | P8: Value | Q8: Volume | R8: Value
A9: 1 | B9: July | C9: 20091.121 | D9: 66928.511 | E9: 14599.875 | F9: 41967.319 | G9: 18020 | H9: 56720 | I9: 12263 | J9: 33288 | K9: 39657 | L9: 29000 | M9: 31545 | N9: 35800 | O9: 47137 | P9: 21500 | Q9: 37176 | R9: 20500
A10: 2 | B10: August | C10: 20566.55 | D10: 68730.44 | E10: 13645.27 | F10: 40672.671 | G10: 14859 | H10: 45707 | I10: 15118 | J10: 41503 | K10: 13944 | L10: 38000 | M10: 4900 | N10: 29700 | O10: 5917 | P10: 19200 | Q10: 7339 | R10: 14800
A11: 3 | B11: September | C11: 14862.631 | D11: 49074.042 | E11: 7070.24 | F11: 22051.148 | G11: 11120 | H11: 30855 | I11: 6575 | J11: 17577 | K11: 7403 | L11: 27400 | M11: 5275 | N11: 14500 | O11: 11540 | P11: 11900 | Q11: 5804 | R11: 13100
A12: 4 | B12: October | C12: 15632.326 | D12: 52749.349 | E12: 8308 | F12: 24272 | G12: 7131 | H12: 20382 | I12: 7939 | J12: 22657 | K12: 18480 | L12: 18500 | M12: 9603 | N12: 6800 | O12: 10090 | P12: 13500 | Q12: 5910 | R12: 9600
A13: 5 | B13: November | C13: 12725.22 | D13: 42699.39 | E13: 5607.095 | F13: 16542.612 | G13: 3709 | H13: 10163 | I13: 4415 | J13: 12729 | K13: 18373 | L13: 18200 | M13: 9413 | N13: 13300 | O13: 15497 | P13: 12700 | Q13: 14853 | R13: 6300
A14: 6 | B14: December | C14: 11223.7 | D14: 40225.804 | E14: 5505.64 | F14: 17416.532 | G14: 4348 | H14: 11154 | I14: 5468 | J14: 16992 | K14: 7435 | L14: 26100 | M14: 11860 | N14: 13700 | O14: 8738 | P14: 8200 | Q14: 24241 | R14: 6500
A15: 7 | B15: January | C15: 13684.487 | D15: 59408.96 | E15: 8342.28 | F15: 29454.384 | G15: 7413 | H15: 19271 | I15: 12722 | J15: 40369 | K15: 1738 | L15: 21300 | M15: 30419 | N15: 18300 | O15: 14107 | P15: 18800 | Q15: 32084 | R15: 6000
A16: 8 | B16: February | C16: 13789.986 | D16: 67256.953 | E16: 11644.64 | F16: 39374.997 | G16: 10073.45 | H16: 27463.541 | I16: 20959 | J16: 66012 | K16: 23997 | L16: 28200 | M16: 18845 | N16: 36100 | O16: 30762 | P16: 26100 | Q16: 9132 | R16: 18000
A17: 9 | B17: March | C17: 18058 | D17: 94300 | E17: 17663 | F17: 56990 | G17: 10924.21 | H17: 29169.929 | I17: 27485 | J17: 85976 | K17: 17661 | L17: 36200 | M17: 24876 | N17: 54100 | O17: 17393 | P17: 41300 | Q17: 14063 | R17: 25300
A18: 10 | B18: April | C18: 17561.14 | D18: 92240.784 | E18: 24629 | F18: 75027 | G18: 10248 | H18: 26250.914 | I18: 20497 | J18: 65808 | K18: 16324 | L18: 38400 | M18: 17009 | N18: 41700 | O18: 17277 | P18: 41200 | Q18: 8277 | R18: 24100
A19: 11 | B19: May | C19: 19473.878 | D19: 107039.25 | E19: 26619 | F19: 79515 | G19: 16596 | H19: 44386 | I19: 19117 | J19: 62463 | K19: 18825 | L19: 43600 | M19: 10184 | N19: 56800 | O19: 15028 | P19: 49300 | Q19: 14418 | R19: 30100
A20: 12 | B20: June | C20: 18448.53 | D20: 100995.74 | E20: 28576.4 | F20: 84971.722 | G20: 19550 | H20: 54314 | I20: 18401 | J20: 60055 | K20: 15849 | L20: 76400 | M20: 14107 | N20: 54600 | O20: 7294 | P20: 53400 | Q20: 9492 | R20: 31300
B21: Total | C21: =SUM(C9:C20) -> 196117.57 | D21: =SUM(D9:D20) -> 841649.22 | E21: =SUM(E9:E20) -> 172210.44 | F21: =SUM(F9:F20) -> 528255.38 | G21: =SUM(G9:G20) -> 133991.66 | H21: =SUM(H9:H20) -> 375836.38 | I21: =SUM(I9:I20) -> 170959 | J21: =SUM(J9:J20) -> 525429 | ... R21: =SUM(R9:R20) -> 205600

Sheet Exports_2007-08
A1: Ethiopian Coffee Exporters' Association
A2: Exported Coffee in Type: July 2007 - June 2008
A3: Volume in Tons and Value in ,000 USD
A5: NO | B5: Coffee Type | C5: Coffee Type by Grade | D5: Volume Tons | E5: Value in 000,USD | F5: Average Price (USD per Ton)
I6: SUMMARY
A7: 1 | B7: SIDAMA | D7: 58003.8 | E7: 193457.4 | F7: =E7*1000/D7 -> 3335.2539 | J7: Volume (ton) | K7: Value (USD) | L7: Avg Price
B8: 1 | C8: SIDAMO GR-2 | D8: 35753.1 | E8: 129058.4 | F8: =E8*1000/D8 -> 3609.7122 | G8: W | I8: Washed | J8: =SUMIF($G$8:$G$82,"W",D$8:D$82) -> 54423.9 | K8: =SUMIF($G$8:$G$82,"W",E$8:E$82) -> 196727.8 | L8: =K8/J8*1000 -> 3614.7318
B9: 2 | C9: SIDAMO GR-4 | D9: 18711.5 | E9: 53478.2 | F9: =E9*1000/D9 -> 2858.0392 | I9: Remainder | J9: =J10-J8 -> 116537 | K9: =K10-K8 -> 328702.8 | L9: =K9/J9*1000 -> 2820.5875
B10: 3 | C10: SIDAMO GR-UG | D10: 1951.2 | E10: 5420.4 | F10: =E10*1000/D10 -> 2777.9828 | G10: W | I10: TOTAL | J10: =D104 -> 170960.9 | K10: =E104 -> 525430.6 | L10: =K10/J10*1000 -> 3073.3963
B11: 4 | C11: SIDAMO PEABERRY | D11: 484.2 | E11: 1413.4 | F11: =E11*1000/D11 -> 2919.0417 | G11: W
B12: 5 | C12: SIDAMO & Mixed With others | D12: 417.5 | E12: 1512.7 | F12: =E12*1000/D12 -> 3623.2335 | G12: W
B13: 6 | C13: SIDAMO | D13: 280.7 | E13: 1131.6 | F13: =E13*1000/D13 -> 4031.3502 | G13: W
B14: 7 | C14: SIDAMO GR-3 | D14: 260.4 | E14: 1055 | F14: =E14*1000/D14 -> 4051.4593
B15: 8 | C15: SIDAMO G.C | D15: 88.8 | E15: 215.3 | F15: =E15*1000/D15 -> 2424.5495
B16: 9 | C16: SIDAMO GR-1 | D16: 29.4 | E16: 101.2 | F16: =E16*1000/D16 -> 3442.1769 | G16: W
B17: 10 | C17: SIDAMO GR-5 | D17: 27 | E17: 71.1 | F17: =E17*1000/D17 -> 2633.3333
A18: 2 | B18: DJIMMA | D18: 49638.2 | E18: 128679.6 | F18: =E18*1000/D18 -> 2592.3502
B19: 1 | C19: DJIMMA GR-5 | D19: 40544.7 | E19: 106666.8 | F19: =E19*1000/D19 -> 2630.8445
B20: 2 | C20: DJIMMA GR-UG | D20: 6588.1 | E20: 15055 | F20: =E20*1000/D20 -> 2285.1809
B21: 3 | C21: DJIMMAH GR-4 | D21: 1740.2 | E21: 4903.3 | F21: =E21*1000/D21 -> 2817.6646
B22: 4 | C22: DJIMMA | D22: 490 | E22: 1282.7 | F22: =E22*1000/D22 -> 2617.7551
B23: 5 | C23: DJIMMAH GR-5 Mixed With Others | D23: 156 | E23: 471.4 | F23: =E23*1000/D23 -> 3021.7949
B24: 6 | C24: DJIMMAH GR-2 | D24: 108 | E24: 274 | F24: =E24*1000/D24 -> 2537.037
B25: 7 | C25: DJIMMA GB | D25: 11.3 | E25: 26.3 | F25: =E25*1000/D25 -> 2327.4336
A26: 3 | B26: LEKEMTIE | D26: 30744.7 | E26: 85611.4 | F26: =E26*1000/D26 -> 2784.5905
B27: 1 | C27: LEKEMITI GR-5 | D27: 24305.4 | E27: 66815 | F27: =E27*1000/D27 -> 2748.9776
B28: 2 | C28: LEKEMPTI GR-4 | D28: 5998.3 | E28: 17508.1 | F28: =E28*1000/D28 -> 2918.8437
B29: 3 | C29: LEKEMITI | D29: 279 | E29: 821.6 | F29: =E29*1000/D29 -> 2944.8029 | G29: W
B30: 4 | C30: LEKEMPTI GR-1 | D30: 108 | E30: 316.7 | F30: =E30*1000/D30 -> 2932.4074 | G30: W
B31: 5 | C31: LEKEMETI GR-5,Mixed with others | D31: 36 | E31: 105.7 | F31: =E31*1000/D31 -> 2936.1111
B32: 6 | C32: LEKEMPTI GR-3 | D32: 18 | E32: 44.4 | F32: =E32*1000/D32 -> 2466.6667
A33: 4 | B33: HARAR | D33: 14193.1 | E33: 50903.7 | F33: =E33*1000/D33 -> 3586.5103
B34: 1 | C34: HARAR GR-5 | D34: 11509 | E34: 40823.2 | F34: =E34*1000/D34 -> 3547.0675
B35: 2 | C35: HARAR GR-4 | D35: 1698 | E35: 6536.3 | F35: =E35*1000/D35 -> 3849.4111
B36: 3 | C36: HARAR GR-UG | D36: 576 | E36: 1825.2 | F36: =E36*1000/D36 -> 3168.75
B37: 4 | C37: HARAR COFFEE | D37: 283.5 | E37: 1140.2 | F37: =E37*1000/D37 -> 4021.8695
B38: 5 | C38: HARAR -4 Mixed with others | D38: 90 | E38: 437.8 | F38: =E38*1000/D38 -> 4864.4444
B39: 6 | C39: HARAR GR-2 | D39: 36.6 | E39: 140.9 | F39: =E39*1000/D39 -> 3849.7268
A40: 5 | B40: YIRGACHEFFE | D40: 6361.5 | E40: 28528 | F40: =E40*1000/D40 -> 4484.4769
B41: 1 | C41: YIRGACHEFFE GR-2 | D41: 4608.5 | E41: 21938.6 | F41: =E41*1000/D41 -> 4760.4644 | G41: W
B42: 2 | C42: YIRGACHEFFE G-2,Mixed with others | D42: 467.4 | E42: 1952 | F42: =E42*1000/D42 -> 4176.2944 | G42: W
B43: 3 | C43: YIRGACHEFFE GR-UG | D43: 402 | E43: 1181.5 | F43: =E43*1000/D43 -> 2939.0547 | G43: W
B44: 4 | C44: YIRGACHEFFE GR-1 | D44: 222.6 | E44: 1027.2 | F44: =E44*1000/D44 -> 4614.5553 | G44: W
B45: 5 | C45: YIRGACHEFFE | D45: 162 | E45: 626.7 | F45: =E45*1000/D45 -> 3868.5185 | G45: W
B46: 6 | C46: YIRGACHEFFE GR-4 | D46: 125.8 | E46: 411.6 | F46: =E46*1000/D46 -> 3271.8601
B47: 7 | C47: YIRGACHEFFE GR-3 | D47: 120 | E47: 499.6 | F47: =E47*1000/D47 -> 4163.3333
B48: 8 | C48: YIRGACHEFFE PEABERRY | D48: 108 | E48: 289.5 | F48: =E48*1000/D48 -> 2680.5556 | G48: W
B49: 9 | C49: YIRGACHEFFE-2 Mixed With others | D49: 54 | E49: 223.8 | F49: =E49*1000/D49 -> 4144.4444 | G49: W
B50: 10 | C50: YERGACHEFFE-2 ORGANIC& HARAR-4 | D50: 36 | E50: 166.9 | F50: =E50*1000/D50 -> 4636.1111 | G50: W
B51: 11 | C51: YIRGACHEFFE GR-5 | D51: 18.6 | E51: 59.5 | F51: =E51*1000/D51 -> 3198.9247
B52: 12 | C52: YIRGACHEFFE KOCHERE GR-4 | D52: 18.6 | E52: 59.9 | F52: =E52*1000/D52 -> 3220.4301
B53: 13 | C53: YIRGACHEFFE KOCHERE GR-5 | D53: 18 | E53: 91.3 | F53: =E53*1000/D53 -> 5072.2222
A54: 6 | B54: LIMMU | D54: 5278.2 | E54: 16668.5 | F54: =E54*1000/D54 -> 3157.9895
B55: 1 | C55: LIMMU GR-2 | D55: 4453.8 | E55: 14547.6 | F55: =E55*1000/D55 -> 3266.3344 | G55: W
B56: 2 | C56: LIMMU GR-UG | D56: 450 | E56: 1116.4 | F56: =E56*1000/D56 -> 2480.8889
B57: 3 | C57: LIMMU PEABERRY | D57: 252 | E57: 570.5 | F57: =E57*1000/D57 -> 2263.8889 | G57: W
B58: 4 | C58: LIMMU & Mixed with others | D58: 71.4 | E58: 246 | F58: =E58*1000/D58 -> 3445.3782 | G58: W
B59: 5 | C59: LIMMU GR-4 | D59: 33 | E59: 135 | F59: =E59*1000/D59 -> 4090.9091
B60: 6 | C60: LIMMU GR-5 | D60: 18 | E60: 53.1 | F60: =E60*1000/D60 -> 2950
A61: 7 | B61: TEPPI | D61: 1840.8 | E61: 5326.3 | F61: =E61*1000/D61 -> 2893.4702
C62: TEPPI GR-2 | D62: 1840.8 | E62: 5326.3 | F62: =E62*1000/D62 -> 2893.4702 | G62: W
A63: 8 | B63: GHIMBI | D63: 1170 | E63: 3356.4 | F63: =E63*1000/D63 -> 2868.7179
C64: GHIMBI GR-4 | D64: 144 | E64: 409.2 | F64: =E64*1000/D64 -> 2841.6667
C65: GHIMBI GR-5 | D65: 1026 | E65: 2947.1 | F65: =E65*1000/D65 -> 2872.4172
A66: 9 | B66: ALL TYPE COFFEE | D66: 1388.4 | E66: 4691.6 | F66: =E66*1000/D66 -> 3379.1415
B67: 1 | C67: Coffee unspecified | D67: 1121.1 | E67: 3954.3 | F67: =E67*1000/D67 -> 3527.1608 | G67: W
B68: 2 | C68: COFFEE GR-4 | D68: 87.3 | E68: 260.9 | F68: =E68*1000/D68 -> 2988.5452
B69: 3 | C69: COFFEE GR-5 | D69: 180 | E69: 476.5 | F69: =E69*1000/D69 -> 2647.2222
A70: 10 | B70: KEFFA FOREST | D70: 456.8 | E70: 2256.8 | F70: =E70*1000/D70 -> 4940.4553
B71: 1 | C71: KAFFA FOREST GR-2 | D71: 403.2 | E71: 2081.3 | F71: =E71*1000/D71 -> 5161.9544 | G71: W
B72: 2 | C72: KAFFA FOREST GR-5 | D72: 53.6 | E72: 175.5 | F72: =E72*1000/D72 -> 3274.2537
A73: 11 | B73: GEMADRO | D73: 252 | E73: 882.4 | F73: =E73*1000/D73 -> 3501.5873
C74: GEMADRO GR-2 | D74: 252 | E74: 882.4 | F74: =E74*1000/D74 -> 3501.5873 | G74: W
A75: 12 | B75: BEBEKA | D75: 576 | E75: 1611.9 | F75: =E75*1000/D75 -> 2798.4375
B76: 1 | C76: BEBEKA GR- 2 | D76: 540 | E76: 1519 | F76: =E76*1000/D76 -> 2812.963 | G76: W
B77: 2 | C77: BEBEKA GR-3 | D77: 36 | E77: 92.8 | F77: =E77*1000/D77 -> 2577.7778
A78: 13 | B78: BALLE | D78: 312 | E78: 1015.2 | F78: =E78*1000/D78 -> 3253.8462
C79: BALE GR-4 | D79: 312 | E79: 1015.2 | F79: =E79*1000/D79 -> 3253.8462
A80: 14 | B80: GUMMER | D80: 126 | E80: 418.2 | F80: =E80*1000/D80 -> 3319.0476
C81: GUMMER GR-1 | D81: 18 | E81: 64.1 | F81: =E81*1000/D81 -> 3561.1111 | G81: W
C82: GUMMER GR-2 | D82: 108 | E82: 354.1 | F82: =E82*1000/D82 -> 3278.7037 | G82: W
A83: 15 | B83: GUDER | D83: 110.4 | E83: 356 | F83: =E83*1000/D83 -> 3224.6377
C84: GODERE GR-2 | D84: 110.4 | E84: 356 | F84: =E84*1000/D84 -> 3224.6377 | G84: W
A85: 16 | B85: BENCH | D85: 86.7 | E85: 244.5 | F85: =E85*1000/D85 -> 2820.0692
B86: 1 | C86: BENCH GR-2 | D86: 18 | E86: 71.8 | F86: =E86*1000/D86 -> 3988.8889 | G86: W
B87: 2 | C87: BENCH GR-5 | D87: 54 | E87: 133.5 | F87: =E87*1000/D87 -> 2472.2222
B88: 3 | C88: BENCH GR-U.G. | D88: 14.7 | E88: 39.2 | F88: =E88*1000/D88 -> 2666.6667
A89: 17 | B89: AMARO | D89: 55.7 | E89: 208.5 | F89: =E89*1000/D89 -> 3743.2675
C90: AMARO GR-4 AMARO GAYO | D90: 37.7 | E90: 139.2 | F90: =E90*1000/D90 -> 3692.3077
C91: AMARO GR2 AMARO GAYO | D91: 18 | E91: 69.3 | F91: =E91*1000/D91 -> 3850 | G91: W
A92: 18 | B92: KEMBATA | D92: 72 | E92: 231.7 | F92: =E92*1000/D92 -> 3218.0556
C93: KENBATA GR-4 | D93: 72 | E93: 231.7 | F93: =E93*1000/D93 -> 3218.0556
A94: 19 | B94: ABYSSIAN | D94: 35.3 | E94: 85 | F94: =E94*1000/D94 -> 2407.932
B95: 1 | C95: ABYSSIIAN MOCCA GR-4 | D95: 18 | E95: 44 | F95: =E95*1000/D95 -> 2444.4444
B96: 2 | C96: ABYSSIIAN MOCCA GR-5 | D96: 17.1 | E96: 39.6 | F96: =E96*1000/D96 -> 2315.7895
B97: 3 | C97: ABYSINIA COFFEE | D97: 0.2 | E97: 1.4 | F97: =E97*1000/D97 -> 7000
A98: 20 | B98: Others | D98: 259.3 | E98: 897.6 | F98: =E98*1000/D98 -> 3461.6275
B99: 1 | C99: KOSSA GR-2 | D99: 108 | E99: 364.2 | F99: =E99*1000/D99 -> 3372.2222 | G99: W
B100: 2 | C100: STAG GR-4 | D100: 50.4 | E100: 154.9 | F100: =E100*1000/D100 -> 3073.4127
B101: 3 | C101: GOLOLCHA GR-3 | D101: 81.6 | E101: 315 | F101: =E101*1000/D101 -> 3860.2941
...

Sheet Exports_2010-11
A1: Ethiopian Coffee Exporters' Association
A2: Exported Coffee in Type: July 2010 - June 2011
A5: NO. | B5: Coffee Type | C5: Coffee Type by Grade | D5: Volume(Ton) | E5: Value (USD) | F5: Average Price
F6: USD per Ton | I6: SUMMARY
A7: 1 | B7: SIDAMA | D7: 66620.617 | E7: 3.2992728e+08 | F7: 4952.33 | J7: Volume (ton) | K7: Value (USD) | L7: Avg Price
B8: 1 | C8: SIDAMO GR-2 | D8: 38236.427 | E8: 2.0912865e+08 | F8: 5469.3565 | G8: W | I8: Washed | J8: =SUMIF($G$8:$G$82,"W",D$8:D$82) -> 62280.322 | K8: =SUMIF($G$8:$G$82,"W",E$8:E$82) -> 3.355446e+08 | L8: =K8/J8 -> 5387.6504
B9: =B8+1 -> 2 | C9: SIDAMO GR-4 | D9: 24691.2 | E9: 1.0526692e+08 | F9: 4263.3375 | I9: Remainder | J9: =J10-J8 -> 133837.61 | K9: =K10-K8 -> 5.0610512e+08 | L9: =K9/J9 -> 3781.4866
B10: =B9+1 -> 3 | C10: SIDAMO GR-UG | D10: 2348.4 | E10: 9747564.3 | F10: 4150.7257 | G10: W | I10: TOTAL | J10: =D82 -> 196117.93 | K10: =E82 -> 8.4164972e+08 | L10: =K10/J10 -> 4291.5491
B11: =B10+1 -> 4 | C11: SIDAMO PEABERRY | D11: 705.6 | E11: 3060285.3 | F11: 4337.139 | G11: W
B12: =B11+1 -> 5 | C12: SIDAMO GR-3 | D12: 334.14 | E12: 1663054.5 | F12: 4977.1189
B13: =B12+1 -> 6 | C13: SIDAMO G.C
B14: =B13+1 -> 7 | C14: SIDAMO GR-1 | G14: W
B15: =B14+1 -> 8 | C15: SIDAMO G-5 | D15: 76.8 | E15: 364868.87 | F15: 4750.8967
B16: =B15+1 -> 9 | C16: Unspecified Grade | D16: 228.05 | E16: 695936 | F16: 3051.6816
A17: 2 | B17: DJIMMA | D17: 54696.45 | E17: 1.851055e+08 | F17: 3384.2324
B18: 1 | C18: DJIMMA GR-5 | D18: 44273.74 | E18: 1.4641192e+08 | F18: 3306.9699
B19: 2 | C19: DJIMMA GR-UG | D19: 7875.71 | E19: 25588887 | F19: 3249.0895
B20: 3 | C20: DJIMMAH GR-4 | D20: 2463 | E20: 12690100 | F20: 5152.2938
B21: 4 | C21: DJIMMA GR-3 | D21: 61.44 | E21: 309931.7 | F21: 5044.4612
B22: 5 | C22: DJIMMAH GR-2 | D22: 22.56 | E22: 104656.02 | F22: 4639.0079
A23: 3 | B23: LEKEMTIE | D23: 31739.18 | E23: 1.1865314e+08 | F23: 3738.3808
B24: 1 | C24: LEKEMITI GR-5 | D24: 27252.14 | E24: 1.0274316e+08 | F24: 3770.0951
B25: 2 | C25: LEKEMPTI GR-4 | D25: 3829.98 | E25: 13565539 | F25: 3541.9346
B26: 3 | C26: LEKEMPTI GR-1 | D26: 1.02 | E26: 4587.3295 | F26: 4497.3818 | G26: W
B27: 4 | C27: LEKEMPTI GR-3 | D27: 92.58 | E27: 424739.56 | F27: 4587.8112
B28: 5 | C28: LEKEMPTI GR-UG | D28: 129.6 | E28: 379579.21 | F28: 2928.8519
B29: 6 | C29: LEKEMPTI GR-2 | D29: 205.86 | E29: 961407.62 | F29: 4670.2012 | G29: W
B30: 7 | C30: Unspecified Grade | D30: 228 | E30: 574129.31 | F30: 2518.111
A31: 4 | B31: HARAR | D31: 16925.35 | E31: 71314463 | F31: 4213.4705
B32: 1 | C32: HARAR GR-5 | D32: 11654.47 | E32: 47539053 | F32: 4079.0403
B33: =B32+1 -> 2 | C33: HARAR GR-4 | D33: 4475.64 | E33: 20954069 | F33: 4681.804
B34: =B33+1 -> 3 | C34: HARAR GR-UG | D34: 703.14 | E34: 2392033.2 | F34: 3401.9301
B35: =B34+1 -> 4 | C35: HARAR GR-1 | D35: 18 | E35: 115081.16 | F35: 6393.3978
B36: =B35+1 -> 5 | C36: HARAR GR-2 | D36: 1.8 | E36: 9809.9996 | F36: 5449.9998
B37: =B36+1 -> 6 | C37: HARAR GR-3 | D37: 27.3 | E37: 135351.95 | F37: 4957.9469
B38: =B37+1 -> 7 | C38: HARAR PEABERY COFFEE | D38: 21 | E38: 60597.16 | F38: 2885.579
B39: =B38+1 -> 8 | C39: Unspecified Grade | D39: 24 | E39: 108467 | F39: 4519.4583
A40: 5 | B40: YIRGACHEFFE | D40: 12126.575 | E40: 69269276 | F40: 5712.188
B41: 1 | C41: YIRGACHEFFE GR-2 | D41: 11221.535 | E41: 65536772 | F41: 5840.268 | G41: W
B42: 2 | C42: YIRGACHEFFE GR-UG | D42: 439.2 | E42: 1762313.1 | F42: 4012.5526 | G42: W
B43: 3 | C43: YIRGACHEFFE GR-1 | D43: 37.02 | E43: 193671.91 | F43: 5231.548 | G43: W
B44: 4 | C44: YIRGACHEFFE GR-4 | D44: 109.2 | E44: 443997.62 | F44: 4065.9123
B45: 5 | C45: YIRGACHEFFE GR-3 | D45: 108 | E45: 521828.82 | F45: 4831.7483
B46: 6 | C46: YIRGACHEFFE PEABERRY | D46: 192.42 | E46: 755666.33 | F46: 3927.1714 | G46: W
B47: 7 | C47: Unspecified Grade | D47: 19.2 | E47: 55026.82 | F47: 2865.9802
A48: 6 | B48: LIMMU | D48: 5894.82 | E48: 29723542 | F48: 5042.3155
B49: 1 | C49: LIMMU GR-2 | D49: 5395.2 | E49: 27511423 | F49: 5099.2407 | G49: W
B50: 2 | C50: LIMMU GR-UG | D50: 114 | E50: 511643.57 | F50: 4488.1015
B51: 3 | C51: LIMMU PEABERRY | D51: 133.2 | E51: 461563.88 | F51: 3465.1943 | G51: W
B52: 4 | C52: LIMMU GR-3 | D52: 180.42 | E52: 982163.85 | F52: 5443.7637
B53: 5 | C53: LIMMU GR-4 | D53: 72 | E53: 256747.56 | F53: 3565.9383
A54: 7 | B54: TEPPI | D54: 1379.1 | E54: 6702090.5 | F54: 4859.7567
B55: 1 | C55: TEPPI GR-2 | D55: 1334.4 | E55: 6502915.9 | F55: 4873.2883 | G55: W
B56: 2 | C56: TEPPI GR-UG | D56: 38.4 | E56: 169313.28 | F56: 4409.2
B57: 3 | C57: Unspecified Grade | D57: 6.3 | E57: 29861.309 | F57: 4739.8904
A58: 8 | B58: GHIMBI | D58: 1093.2 | E58: 3816850.2 | F58: 3491.4473
B59: 1 | C59: GHIMBI GR-4 | D59: 18 | E59: 68254.41 | F59: 3791.9117
B60: 2 | C60: GHIMBI GR-5 | D60: 1036.8 | E60: 3634309.4 | F60: 3505.3138
B61: 3 | C61: Unspecified Grade | D61: 38.4 | E61: 114286.4 | F61: 2976.2083
A62: 9 | B62: KEFFA FOREST | D62: 134.7 | E62: 610388.3 | F62: 4531.4647
B63: 1 | C63: KAFFA FOREST GR-2 | D63: 26.7 | E63: 159392.58 | F63: 5969.7595 | G63: W
B64: 2 | C64: KAFFA FOREST GR-5 | D64: 108 | E64: 450995.72 | F64: 4175.8863
A65: 10 | B65: GEMADRO | D65: 566.4 | E65: 2473471.6 | F65: 4367.0049
B66: 1 | C66: GEMADRO GR-2 | D66: 476.4 | E66: 2205215.8 | F66: 4628.9165 | G66: W
B67: 2 | C67: GEMADRO GR-4
B68: 3 | C68: GEMADRO GR-5 | D68: 90 | E68: 268255.72 | F68: 2980.6191
B69: 4 | C69: Unspecified Grade
A70: 11 | B70: BEBEKA | D70: 870.54 | E70: 4171518.8 | F70: 4791.875
B71: 1 | C71: BEBEKA GR- 2 | D71: 870.54 | E71: 4171518.8 | F71: 4791.875 | G71: W
B72: 2 | C72: BEBEKA GR-3
A73: 12 | B73: GODERE | D73: 620.4 | E73: 3260418.4 | F73: 5255.3488
B74: 1 | C74: GODERE GR-2 | D74: 620.4 | E74: 3260418.4 | F74: 5255.3488 | G74: W
A75: 13 | B75: BENCH | D75: 148.2 | E75: 571115.19 | F75: 3853.6787
B76: 1 | C76: BENCH GR-2 | D76: 36 | E76: 121230.96 | F76: 3367.5266 | G76: W
B77: 2 | C77: BENCH GR-3 | D77: 37.2 | E77: 226139.38 | F77: 6079.0156
B78: 3 | C78: BENCH GR-5
B79: 4 | C79: BENCH GR-U.G. | D79: 75 | E79: 223744.85 | F79: 2983.2647
A80: 14 | B80: Mixed Coffees | D80: 2029.26 | E80: 10686881 | F80: 5266.3931
A81: 15 | B81: Others | D81: 1273.136 | E81: 5363782.6 | F81: 4213.0476
A82: Grand Total | D82: 196117.93 | E82: 8.4164972e+08 | F82: 4291.5491

Sheet Farmer_2010-11
A1: Operating figures for Ethiopian cooperatives in 2010-11
A2: All figures have been converted to green coffee at a ratio of 6 kg cherry to 1 kg green coffee
B4: Weight (kg) | C4: Avg price to farmer ($/kg) | D4: Operating expense ($/kg)
A5: Alaga | B5: 23105.6 | C5: 2.6533791 | D5: 0.49236755
A6: Angecha | B6: 1371.9892 | C6: 1.9924708 | D6: 2.3321693
A7: Anja | B7: 19153.647 | C7: 2.549505 | D7: 0.59416533
A8: Busa | B8: 548.7142 | C8: 2.647095 | D8: 6.6215757
A9: Doyo | B9: 26436.531 | C9: 3.0122138 | D9: 0.57356859
A10: Hunde | B10: 7162.2587 | C10: 2.2263304 | D10: 0.84331482
A11: Ilketinjo | B11: 31098.4 | C11: 2.7319089 | D11: 0.773722
A12: Lelisa | B12: 21083.584 | C12: 2.4723942 | D12: 0.38562182
A13: Sebaka | B13: 40695.387 | C13: 2.2217497 | D13: 0.48662398
A14: Wakito | B14: 28683.942 | C14: 2.6506704 | D14: 0.41851511
A15: Biftu | B15: 8220.7575 | C15: 3.9141645 | D15: 1.0158403
A16: Challa | B16: 18542.311 | C16: 3.6162323 | D16: 0.62776009
... A43: Yayu | B43: 8618.1091 | C43: 2.7058977 | D43: 0.59409867

Sheet Global_Prices
A1: International Coffee Organisation (ICO) Composite and Group Indicator Prices (in US cents per lb)
A3: Calendar Year | B3: 2003 | C3: 2004 | D3: 2005 | E3: 2006 | F3: 2007 | G3: 2008 | H3: 2009 | I3: 2010 | J3: 2011 | K3: 2012
A4: Composite Indicator Price | B4: 51.9 | C4: 62.15 | D4: 89.36 | E4: 95.75 | F4: 107.68 | G4: 124.25 | H4: 115.67 | I4: 147.24 | J4: 210.39 | K4: 156.34
A5: Washed Arabica ("Colombia milds") | B5: 65.33 | C5: 81.44 | D5: 115.73 | E5: 116.8 | F5: 125.57 | G5: 144.32 | H5: 177.39 | I5: 225.52 | J5: 283.87 | K5: 202.08
A6: Other mild Arabica | B6: 64.2 | C6: 80.47 | D6: 114.86 | E6: 114.4 | F6: 123.55 | G6: 139.78 | H6: 143.81 | I6: 195.99 | J6: 271.08 | K6: 186.47
A7: Unwashed Arabica ("Brazilian naturals") | B7: 50.31 | C7: 68.97 | D7: 102.29 | E7: 103.92 | F7: 111.79 | G7: 126.59 | H7: 115.3 | I7: 153.72 | J7: 247.62 | K7: 174.97
A8: Robusta | B8: 36.95 | C8: 35.99 | D8: 50.55 | E8: 67.55 | F8: 86.6 | G8: 105.22 | H8: 74.56 | I8: 78.74 | J8: 109.21 | K8: 102.82

Sheet Worksheet
A2: Indicator | B2: 2007/08 | C2: 2010/11 | D2: Change
A3: Export revenues (US$ thousands) | B3: ='Exports_2007-08'!K10 -> 525430.6 | C3: ='Exports_2010-11'!K10/1000 -> 841649.72 | D3: =(C3-B3)/B3 -> 0.60182852
A4: Export volume (tons) | B4: ='Exports_2007-08'!J10 -> 170960.9 | C4: ='Exports_2010-11'!J10 -> 196117.93 | D4: =(C4-B4)/B4 -> 0.14715077
A5: Avg. export price ($/kg) | B5: =B3/B4 -> 3.0733963 | C5: =C3/C4 -> 4.2915491 | D5: =(C5-B5)/B5 -> 0.39635396
A7: Avg. farmer price ($/kg) | B7: =(B12*B15+B13*B16)/B18*B19 -> 2.3485592 | C7: =SUMPRODUCT('Farmer_2010-11'!C5:C43,'Farmer_2010-11'!B5:B43)/SUM('Farmer_2010-11'!B5:B43) -> 3.0232639 | D7: =(C7-B7)/B7 -> 0.28728449
A8: Share of export | B8: =B7/B5 -> 0.76415763 | C8: =C7/C5 -> 0.70446913 | D8: =(C8-B8)/B8 -> -0.078110182
A9: Costs ($/kg) | B9: =B5-B7 -> 0.72483708 | C9: =C5-C7 -> 1.2682852 | D9: =(C9-B9)/B9 -> 0.74975212
A12: Washed coffee price | B12: 4
A13: Unwashed coffee price | B13: 3.3
A15: Share washed | B15: ='Exports_2007-08'!J8/'Exports_2007-08'!J10 -> 0.31834121
A16: Share unwashed | B16: =1-B15 -> 0.68165879
A18: Exchange rate (Birr to US$) | B18: 9
A19: Conversion factor (cherry to exportable green coffee) | B19: 6
